README.txt
setup.py
ardbeg/__init__.py
ardbeg/ardbeg.py
ardbeg/cli.py
ardbeg/default_settings.py
ardbeg/jinja_filters.py
ardbeg.egg-info/PKG-INFO
ardbeg.egg-info/SOURCES.txt
ardbeg.egg-info/dependency_links.txt
ardbeg.egg-info/entry_points.txt
ardbeg.egg-info/requires.txt
ardbeg.egg-info/top_level.txt
ardbeg/test/__init__.py
ardbeg/test/ardbeg_test.py