Metadata-Version: 1.1
Name: ardbeg
Version: 0.0.1
Summary: Static site generator based on Jinja2.
Home-page: http://pypi.python.org/pypi/ardbeg/
Author: Jon McClure
Author-email: jmcclure@dallasnews.com
License: LICENSE.txt
Platform: UNKNOWN
Classifier: Environment :: Web Environment
Classifier: License :: OSI Approved :: BSD License
Classifier: Operating System :: OS Independent
Classifier: Programming Language :: Python
